Laravel5Doc/README.md
Laravel5Doc/__init__.py
Laravel5Doc/__main__.py
Laravel5Doc/file.epub
Laravel5Doc/index.html
Laravel5Doc/css/__init__.py
Laravel5Doc/css/annotations.css
Laravel5Doc/css/main.css
Laravel5Doc/css/normalize.css
Laravel5Doc/css/popup.css
Laravel5Doc/font/__init__.py
Laravel5Doc/font/fontello.eot
Laravel5Doc/font/fontello.svg
Laravel5Doc/font/fontello.ttf
Laravel5Doc/font/fontello.woff
Laravel5Doc/img/__init__.py
Laravel5Doc/img/annotator-glyph-sprite.png
Laravel5Doc/img/annotator-icon-sprite.png
Laravel5Doc/img/apple-touch-icon.png
Laravel5Doc/img/cancelfullscreen.png
Laravel5Doc/img/close.png
Laravel5Doc/img/fullscreen.png
Laravel5Doc/img/loader.gif
Laravel5Doc/img/menu-icon.png
Laravel5Doc/img/save.png
Laravel5Doc/img/saved.png
Laravel5Doc/img/settings-s.png
Laravel5Doc/img/settings.png
Laravel5Doc/img/star.png
Laravel5Doc/js/__init__.py
Laravel5Doc/js/epub.js
Laravel5Doc/js/epub.min.js
Laravel5Doc/js/epub.min.map
Laravel5Doc/js/hooks.min.js
Laravel5Doc/js/hooks.min.map
Laravel5Doc/js/reader.js
Laravel5Doc/js/reader.js.map
Laravel5Doc/js/reader.min.js
Laravel5Doc/js/reader.min.map
Laravel5Doc/js/hooks/__init__.py
Laravel5Doc/js/hooks/extensions/__init__.py
Laravel5Doc/js/hooks/extensions/highlight.js
Laravel5Doc/js/libs/__init__.py
Laravel5Doc/js/libs/jquery.min.js
Laravel5Doc/js/libs/localforage.min.js
Laravel5Doc/js/libs/screenfull.js
Laravel5Doc/js/libs/screenfull.min.js
Laravel5Doc/js/libs/zip.min.js
Laravel5Doc/js/plugins/__init__.py
Laravel5Doc/js/plugins/hypothesis.js
Laravel5Doc/js/plugins/search.js
laravel_5_doc-2024.3.1.0.dist-info/METADATA
laravel_5_doc-2024.3.1.0.dist-info/WHEEL
laravel_5_doc-2024.3.1.0.dist-info/entry_points.txt
laravel_5_doc-2024.3.1.0.dist-info/top_level.txt
laravel_5_doc-2024.3.1.0.dist-info/RECORD
